README.txt
setup.py
dropbox_tools/__init__.py
dropbox_tools/dropbox_tools.py
dropbox_tools.egg-info/PKG-INFO
dropbox_tools.egg-info/SOURCES.txt
dropbox_tools.egg-info/dependency_links.txt
dropbox_tools.egg-info/not-zip-safe
dropbox_tools.egg-info/requires.txt
dropbox_tools.egg-info/top_level.txt