Metadata-Version: 1.0
Name: dropbox-tools
Version: 1.2
Summary: A collection of command line tools for Dropbox
Home-page: http://github.com/agileronin/dropbox_tools
Author: Gregory Mundy
Author-email: greg.mundy@agileronin.com
License: MIT
Platform: UNKNOWN
